wire_skin/__init__.py
wire_skin/wire_skin.py
wire_skin-0.3.dist-info/DESCRIPTION.rst
wire_skin-0.3.dist-info/METADATA
wire_skin-0.3.dist-info/RECORD
wire_skin-0.3.dist-info/WHEEL
wire_skin-0.3.dist-info/metadata.json
wire_skin-0.3.dist-info/top_level.txt
